hat/event/component.py
hat/event/backends/lmdb/environment.py
hat/event/__init__.py
hat/event/common/subscription/pysubscription.py
hat/event/common/collection/common.py
hat/event/server/engine_runner.py
hat/event/backends/lmdb/convert/main.py
hat/event/common/subscription/common.py
hat/event/backends/lmdb/__init__.py
hat/event/adminer/__init__.py
hat/event/server/main.py
hat/event/backends/memory.py
hat/event/common/module.py
hat/event/backends/lmdb/backend.py
hat/event/manager/__init__.py
hat/event/common/encoder.py
hat/event/common/subscription/csubscription.py
hat/event/server/__init__.py
hat/event/adminer/client.py
hat/event/backends/lmdb/conditions.py
hat/event/common/collection/pylist.py
hat/event/backends/lmdb/manager/main.py
hat/event/backends/lmdb/systemdb.py
hat/event/server/main_runner.py
hat/event/common/common.py
hat/event/server/eventer_server.py
hat/event/server/eventer_client.py
hat/event/backends/lmdb/convert/version.py
hat/event/adminer/common.py
hat/event/common/collection/pytree.py
hat/event/backends/lmdb/timeseriesdb.py
hat/event/backends/__init__.py
hat/event/common/matches.py
hat/event/eventer/common.py
hat/event/backends/lmdb/manager/query.py
hat/event/common/collection/_ctree.abi3.so
hat/event/server/engine.py
hat/event/backends/lmdb/manager/__main__.py
hat/event/backends/lmdb/manager/copy.py
hat/event/eventer/server.py
hat/event/server/__main__.py
hat/event/server/eventer_client_runner.py
hat/event/common/__init__.py
hat/event/common/backend.py
hat/event/manager/__main__.py
hat/event/backends/lmdb/convert/v09.py
hat/event/backends/lmdb/convert/v06.py
hat/event/common/subscription/__init__.py
hat/event/common/collection/__init__.py
hat/event/backends/lmdb/convert/__init__.py
hat/event/manager/main.py
hat/event/backends/lmdb/manager/__init__.py
hat/event/backends/lmdb/latestdb.py
hat/event/backends/dummy.py
hat/event/backends/lmdb/convert/convert_v06_to_v07.py
hat/event/common/subscription/_csubscription.abi3.so
hat/event/eventer/client.py
hat_event-0.9.37.dist-info/LICENSE
hat_event-0.9.37.dist-info/entry_points.txt
hat_event-0.9.37.dist-info/METADATA
hat_event-0.9.37.dist-info/WHEEL
hat_event-0.9.37.dist-info/RECORD
