Metadata-Version: 2.1
Name: hat-event
Version: 0.9.37
Summary: Hat event
License: Apache-2.0
Provides-Extra: dev
Requires-Dist: appdirs ~=1.4.4
Requires-Dist: hat-aio ~=0.7.12
Requires-Dist: hat-drivers ~=0.9.1
Requires-Dist: hat-json ~=0.6.2
Requires-Dist: hat-monitor ~=0.8.19
Requires-Dist: hat-sbs ~=0.7.5
Requires-Dist: hat-util ~=0.6.19
Requires-Dist: lmdb >=1.4.1, <1.7
Requires-Dist: hat-doit ~=0.16.2; extra == 'dev'
Requires-Dist: peru >=1.3.1; extra == 'dev'
Requires-Dist: psutil >=5.9.5; extra == 'dev'
Requires-Dist: sphinxcontrib-plantuml >=0.23; extra == 'dev'
Requires-Dist: sphinxcontrib-programoutput >=0.17; extra == 'dev'
Requires-Python: >=3.10
Project-URL: Homepage, http://hat-open.com
Project-URL: Repository, https://github.com/hat-open/hat-event.git
Project-URL: Documentation, http://hat-event.hat-open.com
